bytedance_profile_data_quality/__init__.py
bytedance_profile_data_quality-0.0.1.dist-info/METADATA
bytedance_profile_data_quality-0.0.1.dist-info/WHEEL
bytedance_profile_data_quality-0.0.1.dist-info/top_level.txt
bytedance_profile_data_quality-0.0.1.dist-info/RECORD
